{"response": {"version": "0.1", "termsofService": "http://www.wunderground.com/weather/api/d/terms.html", "features": {"history": 1}}, "history": {"date": {"pretty": "April 8, 2016", "year": "2016", "mon": "04", "mday": "08", "hour": "00", "min": "00", "tzname": "Europe/Copenhagen"}, "utcdate": {"pretty": "April 7, 2016", "year": "2016", "mon": "04", "mday": "07", "hour": "22", "min": "00", "tzname": "UTC"}, "observations": [{"date": {"pretty": "12:00 AM CEST on April 08, 2016", "year": "2016", "mon": "04", "mday": "08", "hour": "00", "min": "00", "tzname": "Europe/Copenhagen"}, "utcdate": {"pretty": "10:00 PM GMT on April 07, 2016", "year": "2016", "mon": "04", "mday": "07", "hour": "22", "min": "00", "tzname": "UTC"}, "tempm": "6", "tempi": "44", "dewptm": "4", "dewpti": "39", "hum": "76", "wspdm": "24.1", "wspdi": "15.0", "wgustm": "", "wgusti": "", "wdird": "220", "wdire": "SW", "vism": "12", "visi": "7", "pressurem": "1004", "pressurei": "29.66", "windchillm": "-999", "windchilli": "-999", "heatindexm": "-9999", "heatindexi": "-9999", "precipm": "", "precipi": "", "conds": "Light Rain Showers", "icon": "rain", "fog": "0", "rain": "1", "snow": "0", "hail": "0", "thunder": "0", "tornado": "0", "metar": "AAXX 07224 06156 47462 82213 10064 20038 30027 40043 52005 78188 333 55300 20000 81/19 85/25 88/30"}, {"date": {"pretty": "1:00 AM CEST on April 08, 2016", "year": "2016", "mon": "04", "mday": "08", "hour": "01", "min": "00", "tzname": "Europe/Copenhagen"}, "utcdate": {"pretty": "11:00 PM GMT on April 07, 2016", "year": "2016", "mon": "04", "mday": "07", "hour": "23", "min": "00", "tzname": "UTC"}, "tempm": "6", "tempi": "43", "dewptm": "4", "dewpti": "40", "hum": "85", "wspdm": "20.4", "wspdi": "12.7", "wgustm": "", "wgusti": "", "wdird": "220", "wdire": "SW", "vism": "17", "visi": "11", "pressurem": "1004", "pressurei": "29.67", "windchillm": "-999", "windchilli": "-999", "heatindexm": "-9999", "heatindexi": "-9999", "precipm": "", "precipi": "", "conds": "Heavy Drizzle", "icon": "rain", "fog": "0", "rain": "1", "snow": "0", "hail": "0", "thunder": "0", "tornado": "0", "metar": "AAXX 07234 06156 47467 72211 10062 20045 30029 40045 52005 75386 333 55300 20000 81/13 83/16 85/20 87/25"}, {"date": {"pretty": "2:00 AM CEST on April 08, 2016", "year": "2016", "mon": "04", "mday": "08", "hour": "02", "min": "00", "tzname": "Europe/Copenhagen"}, "utcdate": {"pretty": "12:00 AM GMT on April 08, 2016", "year": "2016", "mon": "04", "mday": "08", "hour": "00", "min": "00", "tzname": "UTC"}, "tempm": "6", "tempi": "43", "dewptm": "4", "dewpti": "40", "hum": "85", "wspdm": "20.4", "wspdi": "12.7", "wgustm": "", "wgusti": "", "wdird": "220", "wdire": "SW", "vism": "29", "visi": "18", "pressurem": "1005", "pressurei": "29.67", "windchillm": "-999", "windchilli": "-999", "heatindexm": "-9999", "heatindexi": "-9999", "precipm": "", "precipi": "", "conds": "Clear", "icon": "clear", "fog": "0", "rain": "0", "snow": "0", "hail": "0", "thunder": "0", "tornado": "0", "metar": "AAXX 08004 06156 07579 72211 10062 20044 30030 40046 52006 69921 70086 333 55300 20000 69927 81/21 83/29 85/38 87/58"}, {"date": {"pretty": "3:00 AM CEST on April 08, 2016", "year": "2016", "mon": "04", "mday": "08", "hour": "03", "min": "00", "tzname": "Europe/Copenhagen"}, "utcdate": {"pretty": "1:00 AM GMT on April 08, 2016", "year": "2016", "mon": "04", "mday": "08", "hour": "01", "min": "00", "tzname": "UTC"}, "tempm": "6", "tempi": "43", "dewptm": "4", "dewpti": "40", "hum": "83", "wspdm": "22.2", "wspdi": "13.8", "wgustm": "", "wgusti": "", "wdird": "220", "wdire": "SW", "vism": "35", "visi": "22", "pressurem": "1004", "pressurei": "29.67", "windchillm": "-999", "windchilli": "-999", "heatindexm": "-9999", "heatindexi": "-9999", "precipm": "", "precipi": "", "conds": "Unknown Precipitation", "icon": "unknown", "fog": "0", "rain": "0", "snow": "0", "hail": "0", "thunder": "0", "tornado": "0", "metar": "AAXX 08014 06156 47481 72212 10063 20042 30029 40045 52002 72184 333 55300 20000 81/19 83/38 85/57 87/59"}, {"date": {"pretty": "4:00 AM CEST on April 08, 2016", "year": "2016", "mon": "04", "mday": "08", "hour": "04", "min": "00", "tzname": "Europe/Copenhagen"}, "utcdate": {"pretty": "2:00 AM GMT on April 08, 2016", "year": "2016", "mon": "04", "mday": "08", "hour": "02", "min": "00", "tzname": "UTC"}, "tempm": "6", "tempi": "43", "dewptm": "5", "dewpti": "40", "hum": "86", "wspdm": "18.5", "wspdi": "11.5", "wgustm": "", "wgusti": "", "wdird": "220", "wdire": "SW", "vism": "23", "visi": "14", "pressurem": "1005", "pressurei": "29.67", "windchillm": "-999", "windchilli": "-999", "heatindexm": "-9999", "heatindexi": "-9999", "precipm": "", "precipi": "", "conds": "Light Rain Showers", "icon": "rain", "fog": "0", "rain": "1", "snow": "0", "hail": "0", "thunder": "0", "tornado": "0", "metar": "AAXX 08024 06156 47473 72210 10063 20046 30030 40047 52001 78185 333 55300 20000 81/12 83/15 85/20 87/34"}, {"date": {"pretty": "5:00 AM CEST on April 08, 2016", "year": "2016", "mon": "04", "mday": "08", "hour": "05", "min": "00", "tzname": "Europe/Copenhagen"}, "utcdate": {"pretty": "3:00 AM GMT on April 08, 2016", "year": "2016", "mon": "04", "mday": "08", "hour": "03", "min": "00", "tzname": "UTC"}, "tempm": "6", "tempi": "43", "dewptm": "4", "dewpti": "40", "hum": "85", "wspdm": "18.5", "wspdi": "11.5", "wgustm": "", "wgusti": "", "wdird": "230", "wdire": "SW", "vism": "29", "visi": "18", "pressurem": "1005", "pressurei": "29.68", "windchillm": "-999", "windchilli": "-999", "heatindexm": "-9999", "heatindexi": "-9999", "precipm": "", "precipi": "", "conds": "Drizzle", "icon": "rain", "fog": "0", "rain": "1", "snow": "0", "hail": "0", "thunder": "0", "tornado": "0", "metar": "AAXX 08034 06156 27479 72310 10062 20044 30033 40049 52003 72285 333 55300 20000 69907 81/11 83/17 85/23 87/44"}, {"date": {"pretty": "6:00 AM CEST on April 08, 2016", "year": "2016", "mon": "04", "mday": "08", "hour": "06", "min": "00", "tzname": "Europe/Copenhagen"}, "utcdate": {"pretty": "4:00 AM GMT on April 08, 2016", "year": "2016", "mon": "04", "mday": "08", "hour": "04", "min": "00", "tzname": "UTC"}, "tempm": "6", "tempi": "42", "dewptm": "4", "dewpti": "39", "hum": "83", "wspdm": "14.8", "wspdi": "9.2", "wgustm": "", "wgusti": "", "wdird": "230", "wdire": "SW", "vism": "25", "visi": "16", "pressurem": "1005", "pressurei": "29.68", "windchillm": "-999", "windchilli": "-999", "heatindexm": "-9999", "heatindexi": "-9999", "precipm": "", "precipi": "", "conds": "Scattered Clouds", "icon": "partlycloudy", "fog": "0", "rain": "0", "snow": "0", "hail": "0", "thunder": "0", "tornado": "0", "metar": "AAXX 08044 06156 45475 12308 10055 20037 30035 40051 52006 333 55300 20000 81/15"}, {"date": {"pretty": "7:00 AM CEST on April 08, 2016", "year": "2016", "mon": "04", "mday": "08", "hour": "07", "min": "00", "tzname": "Europe/Copenhagen"}, "utcdate": {"pretty": "5:00 AM GMT on April 08, 2016", "year": "2016", "mon": "04", "mday": "08", "hour": "05", "min": "00", "tzname": "UTC"}, "tempm": "6", "tempi": "42", "dewptm": "4", "dewpti": "40", "hum": "88", "wspdm": "14.8", "wspdi": "9.2", "wgustm": "", "wgusti": "", "wdird": "220", "wdire": "SW", "vism": "23", "visi": "14", "pressurem": "1006", "pressurei": "29.70", "windchillm": "-999", "windchilli": "-999", "heatindexm": "-9999", "heatindexi": "-9999", "precipm": "", "precipi": "", "conds": "Scattered Clouds", "icon": "partlycloudy", "fog": "0", "rain": "0", "snow": "0", "hail": "0", "thunder": "0", "tornado": "0", "metar": "AAXX 08054 06156 45673 72208 10056 20042 30040 40057 52010 333 55300 20025 81/39 87/57"}, {"date": {"pretty": "8:00 AM CEST on April 08, 2016", "year": "2016", "mon": "04", "mday": "08", "hour": "08", "min": "00", "tzname": "Europe/Copenhagen"}, "utcdate": {"pretty": "6:00 AM GMT on April 08, 2016", "year": "2016", "mon": "04", "mday": "08", "hour": "06", "min": "00", "tzname": "UTC"}, "tempm": "6", "tempi": "43", "dewptm": "4", "dewpti": "40", "hum": "83", "wspdm": "14.8", "wspdi": "9.2", "wgustm": "", "wgusti": "", "wdird": "220", "wdire": "SW", "vism": "20", "visi": "12", "pressurem": "1006", "pressurei": "29.72", "windchillm": "-999", "windchilli": "-999", "heatindexm": "-9999", "heatindexi": "-9999", "precipm": "", "precipi": "", "conds": "Clear", "icon": "clear", "fog": "0", "rain": "0", "snow": "0", "hail": "0", "thunder": "0", "tornado": "0", "metar": "AAXX 08064 06156 07670 72208 10059 20042 30046 40062 52013 69922 70085 333 10072 20052 3/005 55300 20166 6///7 70002 83/37 87/47"}, {"date": {"pretty": "9:00 AM CEST on April 08, 2016", "year": "2016", "mon": "04", "mday": "08", "hour": "09", "min": "00", "tzname": "Europe/Copenhagen"}, "utcdate": {"pretty": "7:00 AM GMT on April 08, 2016", "year": "2016", "mon": "04", "mday": "08", "hour": "07", "min": "00", "tzname": "UTC"}, "tempm": "6", "tempi": "43", "dewptm": "5", "dewpti": "40", "hum": "86", "wspdm": "14.8", "wspdi": "9.2", "wgustm": "", "wgusti": "", "wdird": "230", "wdire": "SW", "vism": "19", "visi": "12", "pressurem": "1006", "pressurei": "29.72", "windchillm": "-999", "windchilli": "-999", "heatindexm": "-9999", "heatindexi": "-9999", "precipm": "", "precipi": "", "conds": "Light Rain", "icon": "rain", "fog": "0", "rain": "1", "snow": "0", "hail": "0", "thunder": "0", "tornado": "0", "metar": "AAXX 08074 06156 47469 72308 10062 20046 30048 40064 52013 76164 333 55300 20238 83/12 85/17 87/26"}, {"date": {"pretty": "10:00 AM CEST on April 08, 2016", "year": "2016", "mon": "04", "mday": "08", "hour": "10", "min": "00", "tzname": "Europe/Copenhagen"}, "utcdate": {"pretty": "8:00 AM GMT on April 08, 2016", "year": "2016", "mon": "04", "mday": "08", "hour": "08", "min": "00", "tzname": "UTC"}, "tempm": "6", "tempi": "44", "dewptm": "5", "dewpti": "41", "hum": "85", "wspdm": "14.8", "wspdi": "9.2", "wgustm": "", "wgusti": "", "wdird": "230", "wdire": "SW", "vism": "16", "visi": "10", "pressurem": "1007", "pressurei": "29.73", "windchillm": "-999", "windchilli": "-999", "heatindexm": "-9999", "heatindexi": "-9999", "precipm": "", "precipi": "", "conds": "Light Rain Showers", "icon": "rain", "fog": "0", "rain": "1", "snow": "0", "hail": "0", "thunder": "0", "tornado": "0", "metar": "AAXX 08084 06156 47466 72308 10065 20050 30052 40068 52012 78186 333 55300 20335 81/11 83/16 85/24 87/38"}, {"date": {"pretty": "11:00 AM CEST on April 08, 2016", "year": "2016", "mon": "04", "mday": "08", "hour": "11", "min": "00", "tzname": "Europe/Copenhagen"}, "utcdate": {"pretty": "9:00 AM GMT on April 08, 2016", "year": "2016", "mon": "04", "mday": "08", "hour": "09", "min": "00", "tzname": "UTC"}, "tempm": "8", "tempi": "47", "dewptm": "4", "dewpti": "39", "hum": "65", "wspdm": "22.2", "wspdi": "13.8", "wgustm": "", "wgusti": "", "wdird": "240", "wdire": "WSW", "vism": "24", "visi": "15", "pressurem": "1007", "pressurei": "29.74", "windchillm": "-999", "windchilli": "-999", "heatindexm": "-9999", "heatindexi": "-9999", "precipm": "", "precipi": "", "conds": "Clear", "icon": "clear", "fog": "0", "rain": "0", "snow": "0", "hail": "0", "thunder": "0", "tornado": "0", "metar": "AAXX 08094 06156 27474 72412 10084 20038 30054 40070 52008 70086 333 55303 21307 69907 83/17 85/23 87/36"}, {"date": {"pretty": "12:00 PM CEST on April 08, 2016", "year": "2016", "mon": "04", "mday": "08", "hour": "12", "min": "00", "tzname": "Europe/Copenhagen"}, "utcdate": {"pretty": "10:00 AM GMT on April 08, 2016", "year": "2016", "mon": "04", "mday": "08", "hour": "10", "min": "00", "tzname": "UTC"}, "tempm": "8", "tempi": "47", "dewptm": "4", "dewpti": "38", "hum": "63", "wspdm": "20.4", "wspdi": "12.7", "wgustm": "", "wgusti": "", "wdird": "240", "wdire": "WSW", "vism": "35", "visi": "22", "pressurem": "1007", "pressurei": "29.75", "windchillm": "-999", "windchilli": "-999", "heatindexm": "-9999", "heatindexi": "-9999", "precipm": "", "precipi": "", "conds": "Scattered Clouds", "icon": "partlycloudy", "fog": "0", "rain": "0", "snow": "0", "hail": "0", "thunder": "0", "tornado": "0", "metar": "AAXX 08104 06156 45581 52411 10082 20035 30057 40073 52009 333 55305 21811 81/22 83/36 85/57"}, {"date": {"pretty": "1:00 PM CEST on April 08, 2016", "year": "2016", "mon": "04", "mday": "08", "hour": "13", "min": "00", "tzname": "Europe/Copenhagen"}, "utcdate": {"pretty": "11:00 AM GMT on April 08, 2016", "year": "2016", "mon": "04", "mday": "08", "hour": "11", "min": "00", "tzname": "UTC"}, "tempm": "9", "tempi": "49", "dewptm": "4", "dewpti": "39", "hum": "58", "wspdm": "20.4", "wspdi": "12.7", "wgustm": "", "wgusti": "", "wdird": "240", "wdire": "WSW", "vism": "27", "visi": "17", "pressurem": "1007", "pressurei": "29.75", "windchillm": "-999", "windchilli": "-999", "heatindexm": "-9999", "heatindexi": "-9999", "precipm": "", "precipi": "", "conds": "Partly Cloudy", "icon": "partlycloudy", "fog": "0", "rain": "0", "snow": "0", "hail": "0", "thunder": "0", "tornado": "0", "metar": "AAXX 08114 06156 45577 72411 10092 20037 30057 40073 52005 333 55304 21836 83/25 85/32 87/37"}, {"date": {"pretty": "2:00 PM CEST on April 08, 2016", "year": "2016", "mon": "04", "mday": "08", "hour": "14", "min": "00", "tzname": "Europe/Copenhagen"}, "utcdate": {"pretty": "12:00 PM GMT on April 08, 2016", "year": "2016", "mon": "04", "mday": "08", "hour": "12", "min": "00", "tzname": "UTC"}, "tempm": "9", "tempi": "47", "dewptm": "2", "dewpti": "36", "hum": "57", "wspdm": "22.2", "wspdi": "13.8", "wgustm": "", "wgusti": "", "wdird": "230", "wdire": "SW", "vism": "29", "visi": "18", "pressurem": "1008", "pressurei": "29.75", "windchillm": "-999", "windchilli": "-999", "heatindexm": "-9999", "heatindexi": "-9999", "precipm": "", "precipi": "", "conds": "Clear", "icon": "clear", "fog": "0", "rain": "0", "snow": "0", "hail": "0", "thunder": "0", "tornado": "0", "metar": "AAXX 08124 06156 07579 72312 10086 20025 30059 40075 52005 69901 70086 333 55301 21307 6///7 81/27 87/57"}, {"date": {"pretty": "3:00 PM CEST on April 08, 2016", "year": "2016", "mon": "04", "mday": "08", "hour": "15", "min": "00", "tzname": "Europe/Copenhagen"}, "utcdate": {"pretty": "1:00 PM GMT on April 08, 2016", "year": "2016", "mon": "04", "mday": "08", "hour": "13", "min": "00", "tzname": "UTC"}, "tempm": "8", "tempi": "47", "dewptm": "3", "dewpti": "37", "hum": "59", "wspdm": "22.2", "wspdi": "13.8", "wgustm": "", "wgusti": "", "wdird": "240", "wdire": "WSW", "vism": "30", "visi": "19", "pressurem": "1008", "pressurei": "29.76", "windchillm": "-999", "windchilli": "-999", "heatindexm": "-9999", "heatindexi": "-9999", "precipm": "", "precipi": "", "conds": "Scattered Clouds", "icon": "partlycloudy", "fog": "0", "rain": "0", "snow": "0", "hail": "0", "thunder": "0", "tornado": "0", "metar": "AAXX 08134 06156 45580 52412 10085 20029 30060 40077 52003 333 55304 21696 81/29 83/50 85/58"}, {"date": {"pretty": "4:00 PM CEST on April 08, 2016", "year": "2016", "mon": "04", "mday": "08", "hour": "16", "min": "00", "tzname": "Europe/Copenhagen"}, "utcdate": {"pretty": "2:00 PM GMT on April 08, 2016", "year": "2016", "mon": "04", "mday": "08", "hour": "14", "min": "00", "tzname": "UTC"}, "tempm": "9", "tempi": "49", "dewptm": "1", "dewpti": "34", "hum": "45", "wspdm": "24.1", "wspdi": "15.0", "wgustm": "", "wgusti": "", "wdird": "270", "wdire": "West", "vism": "30", "visi": "19", "pressurem": "1008", "pressurei": "29.76", "windchillm": "-999", "windchilli": "-999", "heatindexm": "-9999", "heatindexi": "-9999", "precipm": "", "precipi": "", "conds": "Scattered Clouds", "icon": "partlycloudy", "fog": "0", "rain": "0", "snow": "0", "hail": "0", "thunder": "0", "tornado": "0", "metar": "AAXX 08144 06156 45580 52713 10094 20013 30060 40076 52003 333 55307 21829 81/32 85/50"}, {"date": {"pretty": "5:00 PM CEST on April 08, 2016", "year": "2016", "mon": "04", "mday": "08", "hour": "17", "min": "00", "tzname": "Europe/Copenhagen"}, "utcdate": {"pretty": "3:00 PM GMT on April 08, 2016", "year": "2016", "mon": "04", "mday": "08", "hour": "15", "min": "00", "tzname": "UTC"}, "tempm": "9", "tempi": "48", "dewptm": "1", "dewpti": "34", "hum": "48", "wspdm": "25.9", "wspdi": "16.1", "wgustm": "", "wgusti": "", "wdird": "260", "wdire": "West", "vism": "35", "visi": "22", "pressurem": "1008", "pressurei": "29.76", "windchillm": "-999", "windchilli": "-999", "heatindexm": "-9999", "heatindexi": "-9999", "precipm": "", "precipi": "", "conds": "Scattered Clouds", "icon": "partlycloudy", "fog": "0", "rain": "0", "snow": "0", "hail": "0", "thunder": "0", "tornado": "0", "metar": "AAXX 08154 06156 25681 32614 10091 20013 30059 40076 54000 333 55306 21408 6///7 81/40 83/58"}, {"date": {"pretty": "6:00 PM CEST on April 08, 2016", "year": "2016", "mon": "04", "mday": "08", "hour": "18", "min": "00", "tzname": "Europe/Copenhagen"}, "utcdate": {"pretty": "4:00 PM GMT on April 08, 2016", "year": "2016", "mon": "04", "mday": "08", "hour": "16", "min": "00", "tzname": "UTC"}, "tempm": "9", "tempi": "49", "dewptm": "2", "dewpti": "35", "hum": "47", "wspdm": "22.2", "wspdi": "13.8", "wgustm": "", "wgusti": "", "wdird": "250", "wdire": "WSW", "vism": "30", "visi": "19", "pressurem": "1007", "pressurei": "29.75", "windchillm": "-999", "windchilli": "-999", "heatindexm": "-9999", "heatindexi": "-9999", "precipm": "", "precipi": "", "conds": "Scattered Clouds", "icon": "partlycloudy", "fog": "0", "rain": "0", "snow": "0", "hail": "0", "thunder": "0", "tornado": "0", "metar": "AAXX 08164 06156 45680 32512 10092 20016 30058 40074 57002 333 55305 20896 81/40 83/58"}, {"date": {"pretty": "7:00 PM CEST on April 08, 2016", "year": "2016", "mon": "04", "mday": "08", "hour": "19", "min": "00", "tzname": "Europe/Copenhagen"}, "utcdate": {"pretty": "5:00 PM GMT on April 08, 2016", "year": "2016", "mon": "04", "mday": "08", "hour": "17", "min": "00", "tzname": "UTC"}, "tempm": "8", "tempi": "47", "dewptm": "2", "dewpti": "36", "hum": "54", "wspdm": "20.4", "wspdi": "12.7", "wgustm": "", "wgusti": "", "wdird": "250", "wdire": "WSW", "vism": "45", "visi": "28", "pressurem": "1008", "pressurei": "29.76", "windchillm": "-999", "windchilli": "-999", "heatindexm": "-9999", "heatindexi": "-9999", "precipm": "", "precipi": "", "conds": "Partly Cloudy", "icon": "partlycloudy", "fog": "0", "rain": "0", "snow": "0", "hail": "0", "thunder": "0", "tornado": "0", "metar": "AAXX 08174 06156 45683 72511 10083 20020 30062 40078 52002 333 55303 20464 83/39 85/48 87/58"}, {"date": {"pretty": "8:00 PM CEST on April 08, 2016", "year": "2016", "mon": "04", "mday": "08", "hour": "20", "min": "00", "tzname": "Europe/Copenhagen"}, "utcdate": {"pretty": "6:00 PM GMT on April 08, 2016", "year": "2016", "mon": "04", "mday": "08", "hour": "18", "min": "00", "tzname": "UTC"}, "tempm": "7", "tempi": "45", "dewptm": "2", "dewpti": "36", "hum": "60", "wspdm": "18.5", "wspdi": "11.5", "wgustm": "", "wgusti": "", "wdird": "260", "wdire": "West", "vism": "40", "visi": "25", "pressurem": "1008", "pressurei": "29.77", "windchillm": "-999", "windchilli": "-999", "heatindexm": "-9999", "heatindexi": "-9999", "precipm": "", "precipi": "", "conds": "Scattered Clouds", "icon": "partlycloudy", "fog": "0", "rain": "0", "snow": "0", "hail": "0", "thunder": "0", "tornado": "0", "metar": "AAXX 08184 06156 05782 52610 10073 20020 30065 40081 52006 69902 333 10100 20059 55300 20094 6///7 81/50 85/58"}, {"date": {"pretty": "9:00 PM CEST on April 08, 2016", "year": "2016", "mon": "04", "mday": "08", "hour": "21", "min": "00", "tzname": "Europe/Copenhagen"}, "utcdate": {"pretty": "7:00 PM GMT on April 08, 2016", "year": "2016", "mon": "04", "mday": "08", "hour": "19", "min": "00", "tzname": "UTC"}, "tempm": "6", "tempi": "43", "dewptm": "2", "dewpti": "36", "hum": "69", "wspdm": "11.1", "wspdi": "6.9", "wgustm": "", "wgusti": "", "wdird": "240", "wdire": "WSW", "vism": "35", "visi": "22", "pressurem": "1009", "pressurei": "29.79", "windchillm": "-999", "windchilli": "-999", "heatindexm": "-9999", "heatindexi": "-9999", "precipm": "", "precipi": "", "conds": "Partly Cloudy", "icon": "partlycloudy", "fog": "0", "rain": "0", "snow": "0", "hail": "0", "thunder": "0", "tornado": "0", "metar": "AAXX 08194 06156 45781 32406 10062 20023 30070 40087 52012 333 55300 20004 83/58"}, {"date": {"pretty": "10:00 PM CEST on April 08, 2016", "year": "2016", "mon": "04", "mday": "08", "hour": "22", "min": "00", "tzname": "Europe/Copenhagen"}, "utcdate": {"pretty": "8:00 PM GMT on April 08, 2016", "year": "2016", "mon": "04", "mday": "08", "hour": "20", "min": "00", "tzname": "UTC"}, "tempm": "5", "tempi": "41", "dewptm": "2", "dewpti": "35", "hum": "73", "wspdm": "11.1", "wspdi": "6.9", "wgustm": "", "wgusti": "", "wdird": "220", "wdire": "SW", "vism": "35", "visi": "22", "pressurem": "1009", "pressurei": "29.79", "windchillm": "-999", "windchilli": "-999", "heatindexm": "-9999", "heatindexi": "-9999", "precipm": "", "precipi": "", "conds": "", "icon": "", "fog": "0", "rain": "0", "snow": "0", "hail": "0", "thunder": "0", "tornado": "0", "metar": "AAXX 08204 06156 45/81 02206 10052 20019 30071 40088 52009 333 55300 20000"}, {"date": {"pretty": "11:00 PM CEST on April 08, 2016", "year": "2016", "mon": "04", "mday": "08", "hour": "23", "min": "00", "tzname": "Europe/Copenhagen"}, "utcdate": {"pretty": "9:00 PM GMT on April 08, 2016", "year": "2016", "mon": "04", "mday": "08", "hour": "21", "min": "00", "tzname": "UTC"}, "tempm": "5", "tempi": "41", "dewptm": "2", "dewpti": "35", "hum": "73", "wspdm": "11.1", "wspdi": "6.9", "wgustm": "", "wgusti": "", "wdird": "230", "wdire": "SW", "vism": "35", "visi": "22", "pressurem": "1009", "pressurei": "29.79", "windchillm": "-999", "windchilli": "-999", "heatindexm": "-9999", "heatindexi": "-9999", "precipm": "", "precipi": "", "conds": "Scattered Clouds", "icon": "partlycloudy", "fog": "0", "rain": "0", "snow": "0", "hail": "0", "thunder": "0", "tornado": "0", "metar": "AAXX 08214 06156 25781 12306 10052 20018 30070 40087 52005 333 55300 20000 6///7 81/58"}], "dailysummary": [{"date": {"pretty": "12:00 AM CEST on April 08, 2016", "year": "2016", "mon": "04", "mday": "08", "hour": "00", "min": "00", "tzname": "Europe/Copenhagen"}, "fog": "0", "rain": "1", "snow": "0", "snowfallm": "", "snowfalli": "", "monthtodatesnowfallm": "", "monthtodatesnowfalli": "", "since1julsnowfallm": "", "since1julsnowfalli": "", "snowdepthm": "", "snowdepthi": "", "hail": "0", "thunder": "0", "tornado": "0", "meantempm": "8", "meantempi": "46", "meandewptm": "3", "meandewpti": "38", "meanpressurem": "1006.67", "meanpressurei": "29.73", "meanwindspdm": "17", "meanwindspdi": "11", "meanwdire": "Variable", "meanwdird": "-1", "meanvism": "23.9", "meanvisi": "14.9", "humidity": "71", "maxtempm": "10", "maxtempi": "50", "mintempm": "5", "mintempi": "41", "maxhumidity": "88", "minhumidity": "45", "maxdewptm": "5", "maxdewpti": "41", "mindewptm": "1", "mindewpti": "34", "maxpressurem": "1009", "maxpressurei": "29.79", "minpressurem": "1004", "minpressurei": "29.66", "maxwspdm": "26", "maxwspdi": "16", "minwspdm": "11", "minwspdi": "7", "maxvism": "30.0", "maxvisi": "19.0", "minvism": "12.0", "minvisi": "7.0", "gdegreedays": "0", "heatingdegreedays": "20", "coolingdegreedays": "0", "precipm": "0.2", "precipi": "0.01", "precipsource": "Precip6GroupSynop", "heatingdegreedaysnormal": "", "monthtodateheatingdegreedays": "", "monthtodateheatingdegreedaysnormal": "", "since1sepheatingdegreedays": "", "since1sepheatingdegreedaysnormal": "", "since1julheatingdegreedays": "", "since1julheatingdegreedaysnormal": "", "coolingdegreedaysnormal": "", "monthtodatecoolingdegreedays": "", "monthtodatecoolingdegreedaysnormal": "", "since1sepcoolingdegreedays": "", "since1sepcoolingdegreedaysnormal": "", "since1jancoolingdegreedays": "", "since1jancoolingdegreedaysnormal": ""}]}}