{"response": {"version": "0.1", "termsofService": "http://www.wunderground.com/weather/api/d/terms.html", "features": {"history": 1}}, "history": {"date": {"pretty": "March 19, 2017", "year": "2017", "mon": "03", "mday": "19", "hour": "00", "min": "00", "tzname": "Europe/Copenhagen"}, "utcdate": {"pretty": "March 18, 2017", "year": "2017", "mon": "03", "mday": "18", "hour": "23", "min": "00", "tzname": "UTC"}, "observations": [{"date": {"pretty": "12:00 AM CET on March 19, 2017", "year": "2017", "mon": "03", "mday": "19", "hour": "00", "min": "00", "tzname": "Europe/Copenhagen"}, "utcdate": {"pretty": "11:00 PM GMT on March 18, 2017", "year": "2017", "mon": "03", "mday": "18", "hour": "23", "min": "00", "tzname": "UTC"}, "tempm": "2", "tempi": "36", "dewptm": "-0", "dewpti": "31", "hum": "76", "wspdm": "13.0", "wspdi": "8.1", "wgustm": "", "wgusti": "", "wdird": "290", "wdire": "WNW", "vism": "25", "visi": "16", "pressurem": "1004", "pressurei": "29.65", "windchillm": "-999", "windchilli": "-999", "heatindexm": "-9999", "heatindexi": "-9999", "precipm": "", "precipi": "", "conds": "", "icon": "", "fog": "0", "rain": "0", "snow": "0", "hail": "0", "thunder": "0", "tornado": "0", "metar": "AAXX 18234 06156 45/75 02907 10021 21004 30023 40039 52020 333 55300 20000"}, {"date": {"pretty": "2:00 AM CET on March 19, 2017", "year": "2017", "mon": "03", "mday": "19", "hour": "02", "min": "00", "tzname": "Europe/Copenhagen"}, "utcdate": {"pretty": "1:00 AM GMT on March 19, 2017", "year": "2017", "mon": "03", "mday": "19", "hour": "01", "min": "00", "tzname": "UTC"}, "tempm": "1", "tempi": "34", "dewptm": "-0", "dewpti": "31", "hum": "86", "wspdm": "13.0", "wspdi": "8.1", "wgustm": "", "wgusti": "", "wdird": "280", "wdire": "West", "vism": "23", "visi": "14", "pressurem": "1006", "pressurei": "29.70", "windchillm": "-999", "windchilli": "-999", "heatindexm": "-9999", "heatindexi": "-9999", "precipm": "", "precipi": "", "conds": "", "icon": "", "fog": "0", "rain": "0", "snow": "0", "hail": "0", "thunder": "0", "tornado": "0", "metar": "AAXX 19014 06156 45/73 02807 10013 21003 30039 40056 52019 333 55300 20000"}, {"date": {"pretty": "3:00 AM CET on March 19, 2017", "year": "2017", "mon": "03", "mday": "19", "hour": "03", "min": "00", "tzname": "Europe/Copenhagen"}, "utcdate": {"pretty": "2:00 AM GMT on March 19, 2017", "year": "2017", "mon": "03", "mday": "19", "hour": "02", "min": "00", "tzname": "UTC"}, "tempm": "1", "tempi": "33", "dewptm": "-0", "dewpti": "31", "hum": "90", "wspdm": "11.1", "wspdi": "6.9", "wgustm": "", "wgusti": "", "wdird": "260", "wdire": "West", "vism": "23", "visi": "14", "pressurem": "1006", "pressurei": "29.71", "windchillm": "-999", "windchilli": "-999", "heatindexm": "-9999", "heatindexi": "-9999", "precipm": "", "precipi": "", "conds": "", "icon": "", "fog": "0", "rain": "0", "snow": "0", "hail": "0", "thunder": "0", "tornado": "0", "metar": "AAXX 19024 06156 45/73 02606 10006 21005 30043 40060 52020 333 55300 20000"}, {"date": {"pretty": "4:00 AM CET on March 19, 2017", "year": "2017", "mon": "03", "mday": "19", "hour": "04", "min": "00", "tzname": "Europe/Copenhagen"}, "utcdate": {"pretty": "3:00 AM GMT on March 19, 2017", "year": "2017", "mon": "03", "mday": "19", "hour": "03", "min": "00", "tzname": "UTC"}, "tempm": "1", "tempi": "33", "dewptm": "-0", "dewpti": "31", "hum": "91", "wspdm": "7.4", "wspdi": "4.6", "wgustm": "", "wgusti": "", "wdird": "260", "wdire": "West", "vism": "23", "visi": "14", "pressurem": "1006", "pressurei": "29.71", "windchillm": "-999", "windchilli": "-999", "heatindexm": "-9999", "heatindexi": "-9999", "precipm": "", "precipi": "", "conds": "", "icon": "", "fog": "0", "rain": "0", "snow": "0", "hail": "0", "thunder": "0", "tornado": "0", "metar": "AAXX 19034 06156 25/73 02604 10007 21004 30042 40059 52009 333 55300 20000 6///7"}, {"date": {"pretty": "5:00 AM CET on March 19, 2017", "year": "2017", "mon": "03", "mday": "19", "hour": "05", "min": "00", "tzname": "Europe/Copenhagen"}, "utcdate": {"pretty": "4:00 AM GMT on March 19, 2017", "year": "2017", "mon": "03", "mday": "19", "hour": "04", "min": "00", "tzname": "UTC"}, "tempm": "0", "tempi": "32", "dewptm": "-1", "dewpti": "30", "hum": "91", "wspdm": "7.4", "wspdi": "4.6", "wgustm": "", "wgusti": "", "wdird": "230", "wdire": "SW", "vism": "20", "visi": "12", "pressurem": "1006", "pressurei": "29.72", "windchillm": "-999", "windchilli": "-999", "heatindexm": "-9999", "heatindexi": "-9999", "precipm": "", "precipi": "", "conds": "", "icon": "", "fog": "0", "rain": "0", "snow": "0", "hail": "0", "thunder": "0", "tornado": "0", "metar": "AAXX 19044 06156 45/70 02304 10000 21009 30047 40063 52008 333 55300 20000"}, {"date": {"pretty": "7:00 AM CET on March 19, 2017", "year": "2017", "mon": "03", "mday": "19", "hour": "07", "min": "00", "tzname": "Europe/Copenhagen"}, "utcdate": {"pretty": "6:00 AM GMT on March 19, 2017", "year": "2017", "mon": "03", "mday": "19", "hour": "06", "min": "00", "tzname": "UTC"}, "tempm": "-0", "tempi": "32", "dewptm": "-1", "dewpti": "30", "hum": "91", "wspdm": "3.7", "wspdi": "2.3", "wgustm": "", "wgusti": "", "wdird": "130", "wdire": "SE", "vism": "21", "visi": "13", "pressurem": "1006", "pressurei": "29.72", "windchillm": "-999", "windchilli": "-999", "heatindexm": "-9999", "heatindexi": "-9999", "precipm": "", "precipi": "", "conds": "Scattered Clouds", "icon": "partlycloudy", "fog": "0", "rain": "0", "snow": "0", "hail": "0", "thunder": "0", "tornado": "0", "metar": "AAXX 19064 06156 05971 11302 11002 21009 30045 40062 52003 6///2 333 10041 21008 3/103 55303 20112 6///7 70025 81/72"}, {"date": {"pretty": "8:00 AM CET on March 19, 2017", "year": "2017", "mon": "03", "mday": "19", "hour": "08", "min": "00", "tzname": "Europe/Copenhagen"}, "utcdate": {"pretty": "7:00 AM GMT on March 19, 2017", "year": "2017", "mon": "03", "mday": "19", "hour": "07", "min": "00", "tzname": "UTC"}, "tempm": "0", "tempi": "32", "dewptm": "-1", "dewpti": "31", "hum": "93", "wspdm": "7.4", "wspdi": "4.6", "wgustm": "", "wgusti": "", "wdird": "190", "wdire": "South", "vism": "18", "visi": "11", "pressurem": "1006", "pressurei": "29.71", "windchillm": "-999", "windchilli": "-999", "heatindexm": "-9999", "heatindexi": "-9999", "precipm": "", "precipi": "", "conds": "Scattered Clouds", "icon": "partlycloudy", "fog": "0", "rain": "0", "snow": "0", "hail": "0", "thunder": "0", "tornado": "0", "metar": "AAXX 19074 06156 45968 11904 10000 21007 30042 40059 57005 333 55300 20241 81/70"}, {"date": {"pretty": "9:00 AM CET on March 19, 2017", "year": "2017", "mon": "03", "mday": "19", "hour": "09", "min": "00", "tzname": "Europe/Copenhagen"}, "utcdate": {"pretty": "8:00 AM GMT on March 19, 2017", "year": "2017", "mon": "03", "mday": "19", "hour": "08", "min": "00", "tzname": "UTC"}, "tempm": "1", "tempi": "33", "dewptm": "0", "dewpti": "33", "hum": "97", "wspdm": "7.4", "wspdi": "4.6", "wgustm": "", "wgusti": "", "wdird": "150", "wdire": "SSE", "vism": "17", "visi": "11", "pressurem": "1005", "pressurei": "29.69", "windchillm": "-999", "windchilli": "-999", "heatindexm": "-9999", "heatindexi": "-9999", "precipm": "", "precipi": "", "conds": "Scattered Clouds", "icon": "partlycloudy", "fog": "0", "rain": "0", "snow": "0", "hail": "0", "thunder": "0", "tornado": "0", "metar": "AAXX 19084 06156 45967 11504 10008 20003 30035 40052 57011 333 55300 20353 81/66"}, {"date": {"pretty": "11:00 AM CET on March 19, 2017", "year": "2017", "mon": "03", "mday": "19", "hour": "11", "min": "00", "tzname": "Europe/Copenhagen"}, "utcdate": {"pretty": "10:00 AM GMT on March 19, 2017", "year": "2017", "mon": "03", "mday": "19", "hour": "10", "min": "00", "tzname": "UTC"}, "tempm": "3", "tempi": "38", "dewptm": "0", "dewpti": "32", "hum": "72", "wspdm": "16.7", "wspdi": "10.4", "wgustm": "", "wgusti": "", "wdird": "150", "wdire": "SSE", "vism": "30", "visi": "19", "pressurem": "1004", "pressurei": "29.65", "windchillm": "-999", "windchilli": "-999", "heatindexm": "-9999", "heatindexi": "-9999", "precipm": "", "precipi": "", "conds": "Scattered Clouds", "icon": "partlycloudy", "fog": "0", "rain": "0", "snow": "0", "hail": "0", "thunder": "0", "tornado": "0", "metar": "AAXX 19104 06156 45980 11509 10032 20001 30023 40039 57019 333 55300 20630 81/62"}, {"date": {"pretty": "12:00 PM CET on March 19, 2017", "year": "2017", "mon": "03", "mday": "19", "hour": "12", "min": "00", "tzname": "Europe/Copenhagen"}, "utcdate": {"pretty": "11:00 AM GMT on March 19, 2017", "year": "2017", "mon": "03", "mday": "19", "hour": "11", "min": "00", "tzname": "UTC"}, "tempm": "4", "tempi": "39", "dewptm": "-0", "dewpti": "32", "hum": "67", "wspdm": "20.4", "wspdi": "12.7", "wgustm": "", "wgusti": "", "wdird": "160", "wdire": "SSE", "vism": "40", "visi": "25", "pressurem": "1004", "pressurei": "29.64", "windchillm": "-999", "windchilli": "-999", "heatindexm": "-9999", "heatindexi": "-9999", "precipm": "", "precipi": "", "conds": "Scattered Clouds", "icon": "partlycloudy", "fog": "0", "rain": "0", "snow": "0", "hail": "0", "thunder": "0", "tornado": "0", "metar": "AAXX 19114 06156 45882 51611 10040 21001 30021 40037 57014 333 55300 20745 81/58 83/60 85/62"}, {"date": {"pretty": "1:00 PM CET on March 19, 2017", "year": "2017", "mon": "03", "mday": "19", "hour": "13", "min": "00", "tzname": "Europe/Copenhagen"}, "utcdate": {"pretty": "12:00 PM GMT on March 19, 2017", "year": "2017", "mon": "03", "mday": "19", "hour": "12", "min": "00", "tzname": "UTC"}, "tempm": "4", "tempi": "40", "dewptm": "0", "dewpti": "32", "hum": "64", "wspdm": "16.7", "wspdi": "10.4", "wgustm": "", "wgusti": "", "wdird": "150", "wdire": "SSE", "vism": "40", "visi": "25", "pressurem": "1003", "pressurei": "29.62", "windchillm": "-999", "windchilli": "-999", "heatindexm": "-9999", "heatindexi": "-9999", "precipm": "", "precipi": "", "conds": "Scattered Clouds", "icon": "partlycloudy", "fog": "0", "rain": "0", "snow": "0", "hail": "0", "thunder": "0", "tornado": "0", "metar": "AAXX 19124 06156 05782 11509 10043 20000 30014 40031 57017 6///1 333 55300 20504 6///7 81/57"}, {"date": {"pretty": "2:00 PM CET on March 19, 2017", "year": "2017", "mon": "03", "mday": "19", "hour": "14", "min": "00", "tzname": "Europe/Copenhagen"}, "utcdate": {"pretty": "1:00 PM GMT on March 19, 2017", "year": "2017", "mon": "03", "mday": "19", "hour": "13", "min": "00", "tzname": "UTC"}, "tempm": "2", "tempi": "36", "dewptm": "1", "dewpti": "33", "hum": "86", "wspdm": "24.1", "wspdi": "15.0", "wgustm": "", "wgusti": "", "wdird": "160", "wdire": "SSE", "vism": "12", "visi": "7", "pressurem": "1002", "pressurei": "29.60", "windchillm": "-999", "windchilli": "-999", "heatindexm": "-9999", "heatindexi": "-9999", "precipm": "", "precipi": "", "conds": "Light Rain", "icon": "rain", "fog": "0", "rain": "1", "snow": "0", "hail": "0", "thunder": "0", "tornado": "0", "metar": "AAXX 19134 06156 47462 51613 10025 20007 30008 40024 57015 76165 333 55300 20432 81/14 85/18"}, {"date": {"pretty": "3:00 PM CET on March 19, 2017", "year": "2017", "mon": "03", "mday": "19", "hour": "15", "min": "00", "tzname": "Europe/Copenhagen"}, "utcdate": {"pretty": "2:00 PM GMT on March 19, 2017", "year": "2017", "mon": "03", "mday": "19", "hour": "14", "min": "00", "tzname": "UTC"}, "tempm": "2", "tempi": "36", "dewptm": "1", "dewpti": "34", "hum": "87", "wspdm": "20.4", "wspdi": "12.7", "wgustm": "", "wgusti": "", "wdird": "150", "wdire": "SSE", "vism": "16", "visi": "10", "pressurem": "1002", "pressurei": "29.58", "windchillm": "-999", "windchilli": "-999", "heatindexm": "-9999", "heatindexi": "-9999", "precipm": "", "precipi": "", "conds": "Light Rain", "icon": "rain", "fog": "0", "rain": "1", "snow": "0", "hail": "0", "thunder": "0", "tornado": "0", "metar": "AAXX 19144 06156 47366 51511 10022 20009 39999 40016 57022 76166 333 55300 20428 81/08 83/16 85/26"}, {"date": {"pretty": "4:00 PM CET on March 19, 2017", "year": "2017", "mon": "03", "mday": "19", "hour": "16", "min": "00", "tzname": "Europe/Copenhagen"}, "utcdate": {"pretty": "3:00 PM GMT on March 19, 2017", "year": "2017", "mon": "03", "mday": "19", "hour": "15", "min": "00", "tzname": "UTC"}, "tempm": "2", "tempi": "36", "dewptm": "1", "dewpti": "33", "hum": "87", "wspdm": "24.1", "wspdi": "15.0", "wgustm": "", "wgusti": "", "wdird": "130", "wdire": "SE", "vism": "21", "visi": "13", "pressurem": "1000", "pressurei": "29.55", "windchillm": "-999", "windchilli": "-999", "heatindexm": "-9999", "heatindexi": "-9999", "precipm": "", "precipi": "", "conds": "Light Rain", "icon": "rain", "fog": "0", "rain": "1", "snow": "0", "hail": "0", "thunder": "0", "tornado": "0", "metar": "AAXX 19154 06156 27371 31313 10020 20008 39988 40005 57026 76165 333 55300 20320 69977 81/08 83/69"}, {"date": {"pretty": "5:00 PM CET on March 19, 2017", "year": "2017", "mon": "03", "mday": "19", "hour": "17", "min": "00", "tzname": "Europe/Copenhagen"}, "utcdate": {"pretty": "4:00 PM GMT on March 19, 2017", "year": "2017", "mon": "03", "mday": "19", "hour": "16", "min": "00", "tzname": "UTC"}, "tempm": "2", "tempi": "36", "dewptm": "1", "dewpti": "34", "hum": "89", "wspdm": "22.2", "wspdi": "13.8", "wgustm": "", "wgusti": "", "wdird": "130", "wdire": "SE", "vism": "7", "visi": "4", "pressurem": "1000", "pressurei": "29.52", "windchillm": "-999", "windchilli": "-999", "heatindexm": "-9999", "heatindexi": "-9999", "precipm": "", "precipi": "", "conds": "Light Rain", "icon": "rain", "fog": "0", "rain": "1", "snow": "0", "hail": "0", "thunder": "0", "tornado": "0", "metar": "AAXX 19164 06156 47357 71312 10020 20011 39980 49997 57028 76165 333 55300 20158 81/07 83/09 85/12 87/19"}, {"date": {"pretty": "6:00 PM CET on March 19, 2017", "year": "2017", "mon": "03", "mday": "19", "hour": "18", "min": "00", "tzname": "Europe/Copenhagen"}, "utcdate": {"pretty": "5:00 PM GMT on March 19, 2017", "year": "2017", "mon": "03", "mday": "19", "hour": "17", "min": "00", "tzname": "UTC"}, "tempm": "2", "tempi": "35", "dewptm": "1", "dewpti": "34", "hum": "92", "wspdm": "22.2", "wspdi": "13.8", "wgustm": "", "wgusti": "", "wdird": "140", "wdire": "SE", "vism": "17", "visi": "11", "pressurem": "999", "pressurei": "29.50", "windchillm": "-999", "windchilli": "-999", "heatindexm": "-9999", "heatindexi": "-9999", "precipm": "", "precipi": "", "conds": "Light Rain", "icon": "rain", "fog": "0", "rain": "1", "snow": "0", "hail": "0", "thunder": "0", "tornado": "0", "metar": "AAXX 19174 06156 47367 71412 10018 20009 39972 49988 57027 76165 333 55300 20058 81/07 83/14 85/17 87/21"}, {"date": {"pretty": "7:00 PM CET on March 19, 2017", "year": "2017", "mon": "03", "mday": "19", "hour": "19", "min": "00", "tzname": "Europe/Copenhagen"}, "utcdate": {"pretty": "6:00 PM GMT on March 19, 2017", "year": "2017", "mon": "03", "mday": "19", "hour": "18", "min": "00", "tzname": "UTC"}, "tempm": "2", "tempi": "35", "dewptm": "1", "dewpti": "33", "hum": "91", "wspdm": "24.1", "wspdi": "15.0", "wgustm": "", "wgusti": "", "wdird": "130", "wdire": "SE", "vism": "11", "visi": "7", "pressurem": "998", "pressurei": "29.48", "windchillm": "-999", "windchilli": "-999", "heatindexm": "-9999", "heatindexi": "-9999", "precipm": "", "precipi": "", "conds": "Light Rain", "icon": "rain", "fog": "0", "rain": "1", "snow": "0", "hail": "0", "thunder": "0", "tornado": "0", "metar": "AAXX 19184 06156 07361 71313 10016 20007 39964 49981 57024 69992 76165 333 10043 21004 55300 20004 69927 81/08 85/10 87/17"}, {"date": {"pretty": "8:00 PM CET on March 19, 2017", "year": "2017", "mon": "03", "mday": "19", "hour": "20", "min": "00", "tzname": "Europe/Copenhagen"}, "utcdate": {"pretty": "7:00 PM GMT on March 19, 2017", "year": "2017", "mon": "03", "mday": "19", "hour": "19", "min": "00", "tzname": "UTC"}, "tempm": "2", "tempi": "35", "dewptm": "1", "dewpti": "34", "hum": "93", "wspdm": "22.2", "wspdi": "13.8", "wgustm": "", "wgusti": "", "wdird": "130", "wdire": "SE", "vism": "6", "visi": "4", "pressurem": "998", "pressurei": "29.47", "windchillm": "-999", "windchilli": "-999", "heatindexm": "-9999", "heatindexi": "-9999", "precipm": "", "precipi": "", "conds": "Light Rain", "icon": "rain", "fog": "0", "rain": "1", "snow": "0", "hail": "0", "thunder": "0", "tornado": "0", "metar": "AAXX 19194 06156 47256 71312 10017 20010 39961 49977 57019 76166 333 55300 20000 81/06 85/08 87/10"}, {"date": {"pretty": "9:00 PM CET on March 19, 2017", "year": "2017", "mon": "03", "mday": "19", "hour": "21", "min": "00", "tzname": "Europe/Copenhagen"}, "utcdate": {"pretty": "8:00 PM GMT on March 19, 2017", "year": "2017", "mon": "03", "mday": "19", "hour": "20", "min": "00", "tzname": "UTC"}, "tempm": "2", "tempi": "35", "dewptm": "1", "dewpti": "34", "hum": "96", "wspdm": "18.5", "wspdi": "11.5", "wgustm": "", "wgusti": "", "wdird": "130", "wdire": "SE", "vism": "12", "visi": "7", "pressurem": "997", "pressurei": "29.44", "windchillm": "-999", "windchilli": "-999", "heatindexm": "-9999", "heatindexi": "-9999", "precipm": "", "precipi": "", "conds": "Light Rain", "icon": "rain", "fog": "0", "rain": "1", "snow": "0", "hail": "0", "thunder": "0", "tornado": "0", "metar": "AAXX 19204 06156 47262 71310 10019 20013 39952 49969 57020 76166 333 55300 20000 81/04 83/07 85/17 87/40"}, {"date": {"pretty": "10:00 PM CET on March 19, 2017", "year": "2017", "mon": "03", "mday": "19", "hour": "22", "min": "00", "tzname": "Europe/Copenhagen"}, "utcdate": {"pretty": "9:00 PM GMT on March 19, 2017", "year": "2017", "mon": "03", "mday": "19", "hour": "21", "min": "00", "tzname": "UTC"}, "tempm": "2", "tempi": "36", "dewptm": "2", "dewpti": "35", "hum": "96", "wspdm": "11.1", "wspdi": "6.9", "wgustm": "", "wgusti": "", "wdird": "140", "wdire": "SE", "vism": "8", "visi": "5", "pressurem": "997", "pressurei": "29.44", "windchillm": "-999", "windchilli": "-999", "heatindexm": "-9999", "heatindexi": "-9999", "precipm": "", "precipi": "", "conds": "Light Rain", "icon": "rain", "fog": "0", "rain": "1", "snow": "0", "hail": "0", "thunder": "0", "tornado": "0", "metar": "AAXX 19214 06156 27258 81406 10023 20018 39952 49968 57012 76165 333 55300 20000 60037 81/06 83/08 88/10"}, {"date": {"pretty": "11:00 PM CET on March 19, 2017", "year": "2017", "mon": "03", "mday": "19", "hour": "23", "min": "00", "tzname": "Europe/Copenhagen"}, "utcdate": {"pretty": "10:00 PM GMT on March 19, 2017", "year": "2017", "mon": "03", "mday": "19", "hour": "22", "min": "00", "tzname": "UTC"}, "tempm": "2", "tempi": "36", "dewptm": "2", "dewpti": "36", "hum": "100", "wspdm": "5.6", "wspdi": "3.5", "wgustm": "", "wgusti": "", "wdird": "130", "wdire": "SE", "vism": "3.6", "visi": "2", "pressurem": "997", "pressurei": "29.45", "windchillm": "-999", "windchilli": "-999", "heatindexm": "-9999", "heatindexi": "-9999", "precipm": "", "precipi": "", "conds": "Light Drizzle", "icon": "rain", "fog": "0", "rain": "1", "snow": "0", "hail": "0", "thunder": "0", "tornado": "0", "metar": "AAXX 19224 06156 47236 81303 10025 20022 39956 49972 57005 75165 333 55300 20000 81/04 85/06 88/08"}], "dailysummary": [{"date": {"pretty": "12:00 AM CET on March 19, 2017", "year": "2017", "mon": "03", "mday": "19", "hour": "00", "min": "00", "tzname": "Europe/Copenhagen"}, "fog": "0", "rain": "1", "snow": "0", "snowfallm": "", "snowfalli": "", "monthtodatesnowfallm": "", "monthtodatesnowfalli": "", "since1julsnowfallm": "", "since1julsnowfalli": "", "snowdepthm": "", "snowdepthi": "", "hail": "0", "thunder": "0", "tornado": "0", "meantempm": "2", "meantempi": "34", "meandewptm": "0", "meandewpti": "33", "meanpressurem": "1002.19", "meanpressurei": "29.60", "meanwindspdm": "12", "meanwindspdi": "8", "meanwdire": "Variable", "meanwdird": "-1", "meanvism": "16.5", "meanvisi": "10.2", "humidity": "87", "maxtempm": "4", "maxtempi": "39", "mintempm": "0", "mintempi": "30", "maxhumidity": "100", "minhumidity": "64", "maxdewptm": "2", "maxdewpti": "36", "mindewptm": "-1", "mindewpti": "30", "maxpressurem": "1006", "maxpressurei": "29.72", "minpressurem": "997", "minpressurei": "29.44", "maxwspdm": "24", "maxwspdi": "15", "minwspdm": "4", "minwspdi": "2", "maxvism": "30.0", "maxvisi": "19.0", "minvism": "3.6", "minvisi": "2.0", "gdegreedays": "0", "heatingdegreedays": "30", "coolingdegreedays": "0", "precipm": "0.9", "precipi": "0.04", "precipsource": "Precip6GroupSynop", "heatingdegreedaysnormal": "", "monthtodateheatingdegreedays": "", "monthtodateheatingdegreedaysnormal": "", "since1sepheatingdegreedays": "", "since1sepheatingdegreedaysnormal": "", "since1julheatingdegreedays": "", "since1julheatingdegreedaysnormal": "", "coolingdegreedaysnormal": "", "monthtodatecoolingdegreedays": "", "monthtodatecoolingdegreedaysnormal": "", "since1sepcoolingdegreedays": "", "since1sepcoolingdegreedaysnormal": "", "since1jancoolingdegreedays": "", "since1jancoolingdegreedaysnormal": ""}]}}